net_uml_draw
