Metadata-Version: 2.1
Name: net-uml-draw
Version: 0.18
Summary: Write PlantUML from a Google Sheet network description
Home-page: https://github.com/j3p0uk/net-uml-draw
Author: JP Sullivan (j3p0uk)
Author-email: j3p0uk@gmail.com
License: UNKNOWN
Project-URL: Bug Reports, https://github.com/j3p0uk/net-uml-draw/issues
Project-URL: Source, https://github.com/j3p0uk/net-uml-draw/
Keywords: network_diagram plantuml google_sheets
Platform: Any
Classifier: Development Status :: 4 - Beta
Classifier: Environment :: Console
Classifier: Intended Audience :: Developers
Classifier: License :: OSI Approved :: MIT License
Classifier: Programming Language :: Python :: 3
Classifier: Programming Language :: Python :: 3.7
Provides: net_uml_draw
